annex4ac/__init__.py
annex4ac/lic_pub.pem
annex4ac/review.py
annex4review-1.1.3.dist-info/licenses/LICENSE
annex4review-1.1.3.dist-info/METADATA
annex4review-1.1.3.dist-info/WHEEL
annex4review-1.1.3.dist-info/top_level.txt
annex4review-1.1.3.dist-info/RECORD
