Metadata-Version: 2.4
Name: annex4review
Version: 1.1.3
Summary: Annex IV Review: analyze PDF documents for EU AI Act compliance
Author-email: Aleksandr Racionalus <prihodko02bk@gmail.com>
License-Expression: MIT
Keywords: AI Act,compliance,review,PDF analysis
Requires-Python: <3.10,>=3.9
License-File: LICENSE
Requires-Dist: spacy==3.6.1
Dynamic: license-file
